<?xml version="1.0" encoding="UTF-8" ?>
<language>
    <type key="4" value="cht" />
    <resource>
        <string keyword="kAllalarmlistisNULL" cht="" />
        <string keyword="kFailedtocreatedirectory" cht="" />
        <string keyword="kHandleAlarm" cht="" />
        <string keyword="kFailedtocreatealllist" cht="" />
        <string keyword="kFailedtocreatelistd" cht="" />
        <string keyword="kMark" cht="" />
        <string keyword="kType" cht="" />
        <string keyword="kPlan" cht="" />
        <string keyword="kCamera" cht="" />
        <string keyword="kForwardingMark" cht="" />
        <string keyword="kLinkageMessage" cht="" />
        <string keyword="kCustomType" cht="" />
        <string keyword="kAlarmbelongtocustomtypedisnotinthedatabase" cht="" />
        <string keyword="kFinished" cht="" />
        <string keyword="kTimedout" cht="" />
        <string keyword="kAlarmisgreaterthan500deletess" cht="" />
        <string keyword="kRemain" cht="" />
        <string keyword="kTimeoutForwarding" cht="" />
        <string keyword="kNocameraislinkedtothealarm" cht="" />
        <string keyword="kDVRdeviceisoffline" cht="" />
        <string keyword="kAlarmhostisoffline" cht="" />
        <string keyword="kProtectivecabinisnotonline" cht="" />
        <string keyword="kTwowayaudiodeviceisoffline" cht="" />
        <string keyword="kHDDFault" cht="" />
        <string keyword="kAccesscontroldeviceisoffline" cht="" />
        <string keyword="kDVRparametersexception" cht="" />
        <string keyword="kAlarmhostdisarmed" cht="" />
        <string keyword="kNotice" cht="" />
        <string keyword="kVideoLoss" cht="" />
        <string keyword="kMotion" cht="" />
        <string keyword="kPrivacyAlarm" cht="" />
        <string keyword="kVideoDiagnosis" cht="" />
        <string keyword="kNormalFace" cht="" />
        <string keyword="kAbnormalFace" cht="" />
        <string keyword="kVCARulesdAlarm" cht="" />
        <string keyword="kRecordingException" cht="" />
        <string keyword="kParametersException" cht="" />
        <string keyword="kDVRIOAlarm" cht="" />
        <string keyword="kArmingRegionAlarm" cht="" />
        <string keyword="kIOalarmprotectioncabin" cht="" />
        <string keyword="kRequestdooralarm" cht="" />
        <string keyword="kOpenevent" cht="" />
        <string keyword="kDuressAlarm" cht="" />
        <string keyword="kDoornormallyopenalarm" cht="" />
        <string keyword="kRequestTalkback" cht="" />
        <string keyword="kAcceptIntercom" cht="" />
        <string keyword="kServerOfflineAlarm" cht="" />
        <string keyword="kTimeExceptionAlarm" cht="" />
        <string keyword="kHumanEntranceAlarm" cht="" />
        <string keyword="kUnknownAlarm" cht="" />
        <string keyword="kAlarmshots" cht="" />
        <string keyword="kAlarmRecording" cht="" />
        <string keyword="kIndex" cht="" />
        <string keyword="kLevelComparison" cht="" />
        <string keyword="kActionMark" cht="" />
        <string keyword="kResult" cht="" />
        <string keyword="kAlarmison" cht="" />
        <string keyword="kUnchecked" cht="" />
        <string keyword="kChecked" cht="" />
        <string keyword="kPleasewaitamoment" cht="" />
        <string keyword="kEintercomandfailure" cht="" />
        <string keyword="kBeingintercom" cht="" />
        <string keyword="kGetthefocuswindowmonitoring" cht="" />
        <string keyword="kLocking" cht="" />
        <string keyword="kUnlocked" cht="" />
        <string keyword="kWhenwritingalocked" cht="" />
        <string keyword="kWritelockfailedstate" cht="" />
        <string keyword="kGetlocaldatadirectoryfailed" cht="" />
        <string keyword="kCommentscannotbeempty" cht="" />
        <string keyword="kDialogueboxisclosing" cht="" />
        <string keyword="kOpeningdialogueboxPleasewait" cht="" />
        <string keyword="kSystemAlarm" cht="" />
        <string keyword="kDeviceAlarm" cht="" />
        <string keyword="kAllAlarms" cht="" />
        <string keyword="kAllalarmsaredisarmed" cht="" />
        <string keyword="kNo" cht="" />
        <string keyword="kAlarmName" cht="" />
        <string keyword="kAlarmType" cht="" />
        <string keyword="kAlarmLevel" cht="" />
        <string keyword="kArmandDisarm" cht="" />
        <string keyword="kRegion" cht="" />
        <string keyword="kLastPage" cht="" />
        <string keyword="kNext" cht="" />
        <string keyword="kSystemAlarmd" cht="" />
        <string keyword="kCameraAlarmd" cht="" />
        <string keyword="kIOAlarmd" cht="" />
        <string keyword="kAccessControlAlarmd" cht="" />
        <string keyword="kTwowayAudiod" cht="" />
        <string keyword="kAnalogAlarmd" cht="" />
        <string keyword="kCompositeAlarmd" cht="" />
        <string keyword="kScheduledAlarmd" cht="" />
        <string keyword="kUpdating" cht="" />
        <string keyword="kUpdatingfailedPleasetryagain" cht="" />
        <string keyword="kAlarmLinkageInformation" cht="" />
        <string keyword="kAlarmnamesAlarmalarmplans" cht="" />
        <string keyword="ksd" cht="" />
        <string keyword="kNoFolder" cht="" />
        <string keyword="kAlarmCapture" cht="" />
        <string keyword="kAll" cht="" />
        <string keyword="kLevel5" cht="" />
        <string keyword="kLevel4" cht="" />
        <string keyword="kLevel3" cht="" />
        <string keyword="kLevel2" cht="" />
        <string keyword="kLevel1" cht="" />
        <string keyword="kTwowayAudio" cht="" />
        <string keyword="kAccessControl" cht="" />
        <string keyword="ksExternalControl" cht="" />
        <string keyword="kThecamerahasnoaccesscontroltolink" cht="" />
        <string keyword="kGettingtwowayaudioinformationfailed" cht="" />
        <string keyword="kIPintercomfailure" cht="" />
        <string keyword="kThisdoesnotsupportremoteaccess" cht="" />
        <string keyword="kOpenDoor" cht="" />
        <string keyword="kCloseDoor" cht="" />
        <string keyword="kCommunicationfailed" cht="" />
        <string keyword="kDoorstatusisunknown" cht="" />
        <string keyword="kDoorisdisconnected" cht="" />
        <string keyword="kThedooropened" cht="" />
        <string keyword="kDoorisopened" cht="" />
        <string keyword="kOpeningdoorfailed" cht="" />
        <string keyword="kThedoorshut" cht="" />
        <string keyword="kDoorisclosed" cht="" />
        <string keyword="kClosingdoorfailed" cht="" />
        <string keyword="kStopTwowayAudio" cht="" />
        <string keyword="kStartTwowayAudio" cht="" />
        <string keyword="kProcessingpleasewait" cht="" />
        <string keyword="kPicturelistgotis0ss" cht="" />
        <string keyword="kAlarmPicture" cht="" />
        <string keyword="kSave" cht="" />
        <string keyword="kSaveAll" cht="" />
        <string keyword="kCreatingpicturedirectoryfailed" cht="" />
        <string keyword="kGettingplaybackinformationfailed" cht="" />
        <string keyword="kGettingchannelinformationfailed" cht="" />
        <string keyword="kBandwidthreachestheupperlimit" cht="" />
        <string keyword="kGettingcameracamIDDinformationfailed" cht="" />
        <string keyword="kApplicationservercamIDd" cht="" />
        <string keyword="kAlarmcapturevideo" cht="" />
        <string keyword="kGetuntreatedalarmfailure" cht="" />
        <string keyword="kFailuretoobtainnotreceived" cht="" />
        <string keyword="kFailedtocreatedatathread" cht="" />
        <string keyword="kTime" cht="" />
        <string keyword="kAlarmHost" cht="" />
        <string keyword="kLevel" cht="" />
        <string keyword="kComments" cht="" />
        <string keyword="kFirstPage" cht="" />
        <string keyword="kPrevious" cht="" />
        <string keyword="kPleaseaddyourcomment" cht="" />
        <string keyword="kSpecialcharacterscannotbecontained" cht="" />
        <string keyword="kPleasechoosethealarmtohandle" cht="" />
        <string keyword="kHandled" cht="" />
        <string keyword="kPagedTotaldPagesTotaldItems" cht="" />
        <string keyword="kAlarmlevelexceedsthenormalranged" cht="" />
        <string keyword="kAllwindowsarelocked" cht="" />
        <string keyword="kLiveviewfailedCameraIDisd" cht="" />
        <string keyword="kVideoIntercom" cht="" />
        <string keyword="kAlarmList" cht="" />
        <string keyword="kTerminalDisplay" cht="" />
        <string keyword="kTwowayAudioControl" cht="" />
        <string keyword="kHandle" cht="" />
        <string keyword="kLock" cht="" />
        <string keyword="kDelete" cht="" />
        <string keyword="kClear" cht="" />
        <string keyword="kOK" cht="" />
        <string keyword="kCancel" cht="" />
        <string keyword="kAlarmHostControl" cht="" />
        <string keyword="kAlarmArmingandDisarming" cht="" />
        <string keyword="kBulkAlarmHandle" cht="" />
        <string keyword="kLegacyalarm" cht="" />
        <string keyword="kAlarmforwardingisenabled" cht="" />
        <string keyword="kSubmit" cht="" />
        <string keyword="kVideoCheck" cht="" />
        <string keyword="kOutputControl" cht="" />
        <string keyword="kIntercomCall" cht="" />
        <string keyword="kNolinkedIOoutput" cht="" />
        <string keyword="kName" cht="" />
        <string keyword="kStatus" cht="" />
        <string keyword="kNopermissiontothemodule" cht="" />
        <string keyword="kVideoPlayback" cht="" />
        <string keyword="kCameraAlarm" cht="" />
        <string keyword="kIOAlarm" cht="" />
        <string keyword="kAccessControlAlarm" cht="" />
        <string keyword="kAnalogAlarm" cht="" />
        <string keyword="kCompositeAlarm" cht="" />
        <string keyword="kScheduledAlarm" cht="" />
        <string keyword="kSubscribealarm" cht="" />
        <string keyword="kShieldedalarm" cht="" />
        <string keyword="kMoreOptions" cht="" />
        <string keyword="kFilltreatmentadvice" cht="" />
        <string keyword="kViewtreatmentadvice" cht="" />
        <string keyword="kAssociationPreview" cht="" />
        <string keyword="kAlarmplans" cht="" />
        <string keyword="kAlarmdetails" cht="" />
        <string keyword="kAssociatedcontrol" cht="" />
        <string keyword="kConfirm" cht="" />
        <string keyword="kForward" cht="" />
        <string keyword="kTemporaryarmanddisarm" cht="" />
        <string keyword="kLocked" cht="" />
        <string keyword="kAllalarm" cht="" />
        <string keyword="kPleaseselecttheitemtobedeleted" cht="" />
        <string keyword="kAreyousuretodeletetheselecteditems" cht="" />
        <string keyword="kSelectthealarmhasbeenprocessed" cht="" />
        <string keyword="kAlarmTime" cht="" />
        <string keyword="kAlarmstatus" cht="" />
        <string keyword="kAlarmCategory" cht="" />
        <string keyword="kProcessingStatus" cht="" />
        <string keyword="kWarningLevel" cht="" />
        <string keyword="kRealtimealarmexdeletedalarm" cht="" />
        <string keyword="kAlarmlevelstatistics" cht="" />
        <string keyword="kTodayalarmgradedistribution" cht="" />
        <string keyword="kRefreshStatistics" cht="" />
        <string keyword="kThetotalnumberofalarms" cht="" />
        <string keyword="kTherearecurrentlynoalarm" cht="" />
        <string keyword="kTherearecurrentlynodatatodisplay" cht="" />
        <string keyword="kSelectallonthispage" cht="" />
        <string keyword="kLegacyleakageelection" cht="" />
        <string keyword="kAltogether" cht="" />
        <string keyword="kThenumberofalarms" cht="" />
        <string keyword="kAlarmtypestatistics" cht="" />
        <string keyword="kTodayhasreceivedthealarmTotal" cht="" />
        <string keyword="kHasbeenprocessed" cht="" />
        <string keyword="kStatisticsTime" cht="" />
        <string keyword="kAlarmName1" cht="" />
        <string keyword="kAlarmType1" cht="" />
        <string keyword="kAlarmplans1" cht="" />
        <string keyword="kDeletealarmsafterconfirmation" cht="" />
        <string keyword="kComments1" cht="" />
        <string keyword="kWarningLevel1" cht="" />
        <string keyword="kRealtimealarm" cht="" />
        <string keyword="kAlarmStatistics" cht="" />
        <string keyword="kAlarmclassificationstatistics" cht="" />
        <string keyword="kUnHandled" cht="" />
        <string keyword="kBlockedAlarm" cht="" />
        <string keyword="kArm" cht="" />
        <string keyword="kDisarm" cht="" />
        <string keyword="kSureToForward" cht="" />
        <string keyword="kForwarding" cht="" />
        <string keyword="kLoadVideoResFail" cht="" />
    </resource>
</language>
