<?xml version="1.0" encoding="UTF-8" ?>
<language>
    <type key="1" value="en" />
    <resource>
        <string keyword="kAllalarmlistisNULL" en="All alarm list is NULL" />
        <string keyword="kFailedtocreatedirectory" en="Failed to create directory." />
        <string keyword="kHandleAlarm" en="Handle Alarm" />
        <string keyword="kFailedtocreatealllist" en="Failed to create all list." />
        <string keyword="kFailedtocreatelistd" en="Failed to create list %d." />
        <string keyword="kMark" en="State" />
        <string keyword="kType" en="Type" />
        <string keyword="kPlan" en="Plan" />
        <string keyword="kCamera" en="Camera" />
        <string keyword="kForwardingMark" en="Forwarding Mark" />
        <string keyword="kLinkageMessage" en="Linkage Message" />
        <string keyword="kCustomType" en="Custom Type" />
        <string keyword="kAlarmbelongtocustomtypedisnotinthedatabase" en="Alarm belong to custom type. %d is not in the database." />
        <string keyword="kFinished" en="Finished." />
        <string keyword="kTimedout" en="Timed out" />
        <string keyword="kAlarmisgreaterthan500deletess" en="There are more than 500 alarms; Delete: %s:%s" />
        <string keyword="kRemain" en="Pending" />
        <string keyword="kTimeoutForwarding" en="Forward When Timed out" />
        <string keyword="kNocameraislinkedtothealarm" en="No camera is linked to the alarm." />
        <string keyword="kDVRdeviceisoffline" en="DVR device is offline." />
        <string keyword="kAlarmhostisoffline" en="Alarm host is offline." />
        <string keyword="kProtectivecabinisnotonline" en="ATM secure room is offline." />
        <string keyword="kTwowayaudiodeviceisoffline" en="Two-way audio device is offline." />
        <string keyword="kHDDFault" en="HDD Fault" />
        <string keyword="kAccesscontroldeviceisoffline" en="Access control device is offline." />
        <string keyword="kDVRparametersexception" en="DVR parameters exception" />
        <string keyword="kAlarmhostdisarmed" en="Alarm host disarmed." />
        <string keyword="kNotice" en="Notice" />
        <string keyword="kVideoLoss" en="Video Loss" />
        <string keyword="kMotion" en="Motion" />
        <string keyword="kPrivacyAlarm" en="Privacy Alarm" />
        <string keyword="kVideoDiagnosis" en="Video Diagnosis" />
        <string keyword="kNormalFace" en="Normal Face" />
        <string keyword="kAbnormalFace" en="Abnormal Face" />
        <string keyword="kVCARulesdAlarm" en="VCA Rules %d Alarm" />
        <string keyword="kRecordingException" en="Recording Exception" />
        <string keyword="kParametersException" en="Parameters Exception" />
        <string keyword="kDVRIOAlarm" en="DVR IO Alarm" />
        <string keyword="kArmingRegionAlarm" en="Arming Region Alarm" />
        <string keyword="kIOalarmprotectioncabin" en="ATM secure room IO alarm" />
        <string keyword="kRequestdooralarm" en="Open Door Request" />
        <string keyword="kOpenevent" en="Open Door Event" />
        <string keyword="kDuressAlarm" en="Duress Alarm" />
        <string keyword="kDoornormallyopenalarm" en="Door Normally Open " />
        <string keyword="kRequestTalkback" en="Two-way Audio Request" />
        <string keyword="kAcceptIntercom" en="Accept Two-way Audio" />
        <string keyword="kServerOfflineAlarm" en="Server Offline " />
        <string keyword="kTimeExceptionAlarm" en="Time Exception " />
        <string keyword="kHumanEntranceAlarm" en="Human Entrance " />
        <string keyword="kUnknownAlarm" en="Unknown " />
        <string keyword="kAlarmshots" en="Picture" />
        <string keyword="kAlarmRecording" en="Video" />
        <string keyword="kIndex" en="Index" />
        <string keyword="kLevelComparison" en="Level Comparison" />
        <string keyword="kActionMark" en="Action Mark" />
        <string keyword="kResult" en="Result" />
        <string keyword="kAlarmison" en="Alarm is on." />
        <string keyword="kUnchecked" en="Unchecked" />
        <string keyword="kChecked" en="Checked" />
        <string keyword="kPleasewaitamoment" en="Please wait a moment…" />
        <string keyword="kEintercomandfailure" en="E-home Two-way Audio Failed." />
        <string keyword="kBeingintercom" en="Two-way audio is on." />
        <string keyword="kGetthefocuswindowmonitoring" en="Failed to get the camera information." />
        <string keyword="kLocking" en="Locking" />
        <string keyword="kUnlocked" en="Unlocked" />
        <string keyword="kWhenwritingalocked" en="" />
        <string keyword="kWritelockfailedstate" en="" />
        <string keyword="kGetlocaldatadirectoryfailed" en="Failed to get localdata directory." />
        <string keyword="kCommentscannotbeempty" en="Comments cannot be empty." />
        <string keyword="kDialogueboxisclosing" en="Dialogue box is closing." />
        <string keyword="kOpeningdialogueboxPleasewait" en="Opening dialogue box. Please wait…" />
        <string keyword="kSystemAlarm" en="System Alarm " />
        <string keyword="kDeviceAlarm" en="Device Alarm" />
        <string keyword="kAllAlarms" en="All Alarms " />
        <string keyword="kAllalarmsaredisarmed" en="All alarms are disarmed." />
        <string keyword="kNo" en="No." />
        <string keyword="kAlarmName" en="Alarm Name" />
        <string keyword="kAlarmType" en="Alarm Type" />
        <string keyword="kAlarmLevel" en="Alarm Level" />
        <string keyword="kArmandDisarm" en="Arm and Disarm" />
        <string keyword="kRegion" en="Region" />
        <string keyword="kLastPage" en="Last Page" />
        <string keyword="kNext" en="Next" />
        <string keyword="kSystemAlarmd" en="System Alarm (%d)" />
        <string keyword="kCameraAlarmd" en="Camera Alarm (%d)" />
        <string keyword="kIOAlarmd" en="I/O Alarm (%d)" />
        <string keyword="kAccessControlAlarmd" en="Access Control Alarm (%d)" />
        <string keyword="kTwowayAudiod" en="Two-way Audio (%d)" />
        <string keyword="kAnalogAlarmd" en="Analog Alarm (%d)" />
        <string keyword="kCompositeAlarmd" en="Composite Alarm (%d)" />
        <string keyword="kScheduledAlarmd" en="Scheduled Alarm (%d)" />
        <string keyword="kUpdating" en="Updating…" />
        <string keyword="kUpdatingfailedPleasetryagain" en="Updating failed. Please try again." />
        <string keyword="kAlarmLinkageInformation" en="Alarm Linkage Information" />
        <string keyword="kAlarmnamesAlarmalarmplans" en="Alarm Host Name:%s\n\n &lt;Alarm Type&gt;: %s\n\n &lt;Alarm Level&gt;: %s\n\n &lt;Alarm Plan&gt; %s\n\n" />
        <string keyword="ksd" en="%s-%d" />
        <string keyword="kNoFolder" en="No Folder" />
        <string keyword="kAlarmCapture" en="Alarm Capture" />
        <string keyword="kAll" en="All" />
        <string keyword="kLevel5" en="Level 5" />
        <string keyword="kLevel4" en="Level 4" />
        <string keyword="kLevel3" en="Level 3" />
        <string keyword="kLevel2" en="Level 2" />
        <string keyword="kLevel1" en="Level 1" />
        <string keyword="kTwowayAudio" en="Two-way Audio" />
        <string keyword="kAccessControl" en="Access Control" />
        <string keyword="ksExternalControl" en="%s External Control" />
        <string keyword="kThecamerahasnoaccesscontroltolink" en="The camera has no access control to link." />
        <string keyword="kGettingtwowayaudioinformationfailed" en="Getting two-way audio information failed." />
        <string keyword="kIPintercomfailure" en="Failed to start IP two-way audio." />
        <string keyword="kThisdoesnotsupportremoteaccess" en="The access control cannot be operated remotely." />
        <string keyword="kOpenDoor" en="Open Door" />
        <string keyword="kCloseDoor" en="Close Door" />
        <string keyword="kCommunicationfailed" en="Communication failed." />
        <string keyword="kDoorstatusisunknown" en="Door status is unknown." />
        <string keyword="kDoorisdisconnected" en="Door is disconnected." />
        <string keyword="kThedooropened" en="The door is opened." />
        <string keyword="kDoorisopened" en="Door is opened." />
        <string keyword="kOpeningdoorfailed" en="Opening door failed." />
        <string keyword="kThedoorshut" en="The door is closed." />
        <string keyword="kDoorisclosed" en="Door is closed." />
        <string keyword="kClosingdoorfailed" en="Closing door failed." />
        <string keyword="kStopTwowayAudio" en="Stop Two-way Audio" />
        <string keyword="kStartTwowayAudio" en="Start Two-way Audio" />
        <string keyword="kProcessingpleasewait" en="Processing…please wait." />
        <string keyword="kPicturelistgotis0ss" en="Picture list got is 0%s%s" />
        <string keyword="kAlarmPicture" en="Alarm Picture" />
        <string keyword="kSave" en="Save" />
        <string keyword="kSaveAll" en="Save All" />
        <string keyword="kCreatingpicturedirectoryfailed" en="Creating picture directory failed." />
        <string keyword="kGettingplaybackinformationfailed" en="Getting playback information failed." />
        <string keyword="kGettingchannelinformationfailed" en="Getting channel information failed." />
        <string keyword="kBandwidthreachestheupperlimit" en="Bandwidth reaches the upper limit." />
        <string keyword="kGettingcameracamIDDinformationfailed" en="Getting camera [camID:%D] information failed." />
        <string keyword="kApplicationservercamIDd" en="Failed to request load balance server. [camID:%D]" />
        <string keyword="kAlarmcapturevideo" en="Video and Picture" />
        <string keyword="kGetuntreatedalarmfailure" en="Failed to get unprocessed alarm information." />
        <string keyword="kFailuretoobtainnotreceived" en="Failed to get unaccepted alarm information." />
        <string keyword="kFailedtocreatedatathread" en="Failed to create data thread." />
        <string keyword="kTime" en="Time" />
        <string keyword="kAlarmHost" en="Alarm Host" />
        <string keyword="kLevel" en="Level" />
        <string keyword="kComments" en="Remark" />
        <string keyword="kFirstPage" en="First Page" />
        <string keyword="kPrevious" en="Previous" />
        <string keyword="kPleaseaddyourcomment" en="Please add your comment." />
        <string keyword="kSpecialcharacterscannotbecontained" en="Special characters cannot be contained." />
        <string keyword="kPleasechoosethealarmtohandle" en="Please choose the alarm to handle." />
        <string keyword="kHandled" en="Handled" />
        <string keyword="kPagedTotaldPagesTotaldItems" en="%d~%d Total %d Items" />
        <string keyword="kAlarmlevelexceedsthenormalranged" en="Alarm level exceeds the normal range: %d" />
        <string keyword="kAllwindowsarelocked" en="All windows are locked." />
        <string keyword="kLiveviewfailedCameraIDisd" en="Live view failed. Camera ID is %d." />
        <string keyword="kVideoIntercom" en="Video Intercom" />
        <string keyword="kAlarmList" en="Alarm List" />
        <string keyword="kTerminalDisplay" en="Terminal Display" />
        <string keyword="kTwowayAudioControl" en="Two-way Audio Control" />
        <string keyword="kHandle" en="Handle" />
        <string keyword="kLock" en="Lock" />
        <string keyword="kDelete" en="Delete" />
        <string keyword="kClear" en="Clear" />
        <string keyword="kOK" en="OK" />
        <string keyword="kCancel" en="Cancel" />
        <string keyword="kAlarmHostControl" en="Alarm Host Control" />
        <string keyword="kAlarmArmingandDisarming" en="Alarm Arming and Disarming" />
        <string keyword="kBulkAlarmHandle" en="Bulk Alarm Handle" />
        <string keyword="kLegacyalarm" en="Pending" />
        <string keyword="kAlarmforwardingisenabled" en="Alarm forwarding function is enabled." />
        <string keyword="kSubmit" en="Submit" />
        <string keyword="kVideoCheck" en="Video Re-Check" />
        <string keyword="kOutputControl" en="Output Control" />
        <string keyword="kIntercomCall" en="Start Two-way Audio" />
        <string keyword="kNolinkedIOoutput" en="No linked IO output." />
        <string keyword="kName" en="Name" />
        <string keyword="kStatus" en="Status" />
        <string keyword="kNopermissiontothemodule" en="No permission to the module." />
        <string keyword="kVideoPlayback" en="Video Playback" />
        <string keyword="kCameraAlarm" en="Camera Alarm" />
        <string keyword="kIOAlarm" en="I/O Alarm" />
        <string keyword="kAccessControlAlarm" en="Access Control Alarm" />
        <string keyword="kAnalogAlarm" en="Analog Alarm" />
        <string keyword="kCompositeAlarm" en="Composite Alarm" />
        <string keyword="kScheduledAlarm" en="Scheduled Alarm" />
        <string keyword="kSubscribealarm" en="Subsribe Alarm" />
        <string keyword="kShieldedalarm" en="Shield Alarm" />
        <string keyword="kMoreOptions" en="More Options" />
        <string keyword="kFilltreatmentadvice" en="Enter Handling Method" />
        <string keyword="kViewtreatmentadvice" en="Check Handling Method" />
        <string keyword="kAssociationPreview" en="Link Live View" />
        <string keyword="kAlarmplans" en="Alarm Plan" />
        <string keyword="kAlarmdetails" en="Alarm Detail" />
        <string keyword="kAssociatedcontrol" en="Alarm Control" />
        <string keyword="kConfirm" en="OK" />
        <string keyword="kForward" en="Forward" />
        <string keyword="kTemporaryarmanddisarm" en="Arm/Disarm" />
        <string keyword="kLocked" en="Locked" />
        <string keyword="kAllalarm" en="All Alarms" />
        <string keyword="kPleaseselecttheitemtobedeleted" en="Please select the item to delete." />
        <string keyword="kAreyousuretodeletetheselecteditems" en="Are you sure to delete the selected items?" />
        <string keyword="kSelectthealarmhasbeenprocessed" en="The selected alarm is handled." />
        <string keyword="kAlarmTime" en="Alarm Time" />
        <string keyword="kAlarmstatus" en="Alarm Status" />
        <string keyword="kAlarmCategory" en="Alarm Type" />
        <string keyword="kProcessingStatus" en="Handle Status" />
        <string keyword="kWarningLevel" en="Alarm Level" />
        <string keyword="kRealtimealarmexdeletedalarm" en="The live alarm is more than %d, delete the alarm automatically." />
        <string keyword="kAlarmlevelstatistics" en="Alarm Level Statistics" />
        <string keyword="kTodayalarmgradedistribution" en="Distribution Today" />
        <string keyword="kRefreshStatistics" en="Refresh Statistics Information" />
        <string keyword="kThetotalnumberofalarms" en="Alarm Total" />
        <string keyword="kTherearecurrentlynoalarm" en="No Alarm" />
        <string keyword="kTherearecurrentlynodatatodisplay" en="No data display." />
        <string keyword="kSelectallonthispage" en="Select All " />
        <string keyword="kLegacyleakageelection" en="Legacy" />
        <string keyword="kAltogether" en="Total" />
        <string keyword="kThenumberofalarms" en="Alarms" />
        <string keyword="kAlarmtypestatistics" en="Alarm type statistics" />
        <string keyword="kTodayhasreceivedthealarmTotal" en="Today received :" />
        <string keyword="kHasbeenprocessed" en="processed:" />
        <string keyword="kStatisticsTime" en="Statistics:" />
        <string keyword="kAlarmName1" en="Alarm Name:" />
        <string keyword="kAlarmType1" en="Alarm Type:" />
        <string keyword="kAlarmplans1" en="Alarm plan:" />
        <string keyword="kDeletealarmsafterconfirmation" en="Remove the alarm after confirmation" />
        <string keyword="kComments1" en="Comments" />
        <string keyword="kWarningLevel1" en="Alarm Level:" />
        <string keyword="kRealtimealarm" en="Real-time alarm" />
        <string keyword="kAlarmStatistics" en="Alarm Statistics" />
        <string keyword="kAlarmclassificationstatistics" en="Alarm classification statistics" />
        <string keyword="kUnHandled" en="UnHandled" />
        <string keyword="kBlockedAlarm" en="Blocked alarm" />
        <string keyword="kArm" en="Arm" />
        <string keyword="kDisarm" en="Disarm" />
        <string keyword="kSureToForward" en="Are you sure you forward the selected items?" />
        <string keyword="kForwarding" en="Forwarding" />
        <string keyword="kLoadVideoResFail" en="Loading video intercom resource failed" />
        <string keyword="kLiveviewFailed" en="Live view failed." />
        <string keyword="kStopAlarm" en="Stop Alarm" />
        <string keyword="kStopAlarmSure" en="Are you sure you select the item to stop it?" />
        <string keyword="kStoping" en="Sending a stop command" />
        <string keyword="kalarmlimitstoptime" en="" />
        <string keyword="kAlarmTime2" en="Alarm Time:" />
        <string keyword="kAlarmName2" en="Alarm Name:" />
        <string keyword="kAlarmInfo2" en="Alarm Info:" />
        <string keyword="kSpecialcharacterscannotbecontained1" en="Can not contain the following characters:" />
        <string keyword="kForwardingFeatureIsNotEnabled" en="Please enable forwarding the client configuration" />
        <string keyword="kLoadingData" en="Loading data…" />
        <string keyword="kProcessingFailed" en="Processing failed" />
        <string keyword="kConversionRecvToUnhadnleFail" en="Conversion is not receive alerts for unprocessed alarm failure" />
        <string keyword="kSendStopCmdOK" en="Stop command sent successfully" />
        <string keyword="kFmtPageIndex" en="%d Records Total, Page %d / %d" />
        <string keyword="kAlarmRegion" en="Alarm Region" />
        <string keyword="KVIDEOREVIEWISBLOCKED" en="Double-click to open the preview" />
        <string keyword="KNOASSOCAM" en="Associate camera not exist." />
        <string keyword="kAlarmProperty" en="Alarm property" />
        <string keyword="kAlarmPropertyTest" en="Test" />
        <string keyword="kAlarmPropertyWrong" en="Wrong" />
        <string keyword="kAlarmPropertyReal" en="Alarm" />
        <string keyword="kAlarmPropertyNotSet" en="Not set" />
        <string keyword="kAlarmDelay" en="Delay" />
        <string keyword="kLeaveAlarmProperty" en="Property" />
        <string keyword="kLoading" en="Loading, please wait…" />
        <string keyword="kPictureMiss" en="Pictures are not existing!" />
        <string keyword="kNotFoundRecentRecord" en="Recent record not found!" />
        <string keyword="kShowHistory" en="Show History" />
        <string keyword="kCloseHistory" en="Close History" />
        <string keyword="kNoAssoControl" en="Can not find associate controls" />
        <string keyword="kAssoPlayback" en="Associate playback" />
        <string keyword="kAssoPicture" en="Associate picture" />
        <string keyword="kUserNotSet" en="User not set" />
        <string keyword="kRegionInfo" en="Region info" />
        <string keyword="kDealInfo" en="Deal info" />
        <string keyword="kRehandle" en="Rehandle" />
        <string keyword="kRehandleWarning" en="This operation will cover others&apos; deal mind, are you sure?" />
    </resource>
</language>
