<?xml version="1.0" encoding="UTF-8" ?>
<language>
    <type key="4" value="cht" />
    <resource>
        <string keyword="vt_main_btn_starttalk" cht="" />
        <string keyword="vt_main_btn_stoptalk" cht="" />
        <string keyword="vt_main_tip_clear" cht="" />
        <string keyword="vt_main_tip_delete" cht="" />
        <string keyword="vt_main_tip_lock" cht="" />
        <string keyword="vt_main_list_index" cht="" />
        <string keyword="vt_main_list_time" cht="" />
        <string keyword="vt_main_list_alarmname" cht="" />
        <string keyword="vt_main_list_status" cht="" />
        <string keyword="vt_main_list_handle" cht="" />
        <string keyword="vt_main_list_grade" cht="" />
        <string keyword="vt_main_st_grade1" cht="" />
        <string keyword="vt_main_st_grade2" cht="" />
        <string keyword="vt_main_st_grade3" cht="" />
        <string keyword="vt_main_st_grade4" cht="" />
        <string keyword="vt_main_st_grade5" cht="" />
        <string keyword="vt_main_st_gradeunknown" cht="" />
        <string keyword="vt_main_st_capturepath" cht="" />
        <string keyword="vt_tip_getcamerainfo_failed" cht="" />
        <string keyword="vt_tip_preview_failed" cht="" />
        <string keyword="vt_tip_talk_failed" cht="" />
        <string keyword="vt_tip_no_talkchannel" cht="" />
        <string keyword="vt_tip_talktype_nosupport" cht="" />
        <string keyword="vt_tip_login_failed" cht="" />
        <string keyword="vt_tip_clear_allitem" cht="" />
        <string keyword="vt_tip_select_alarmitem" cht="" />
        <string keyword="vt_tip_delete_item" cht="" />
        <string keyword="vt_tip_loginvag_failed" cht="" />
        <string keyword="vt_tip_vagtalk_failed" cht="" />
        <string keyword="vt_tip_loadregionres_failed" cht="" />
        <string keyword="vt_tip_alarming" cht="" />
        <string keyword="vt_tip_finished" cht="" />
        <string keyword="vt_tip_unknown_status" cht="" />
        <string keyword="vt_tip_checked" cht="" />
        <string keyword="vt_tip_uncheck" cht="" />
    </resource>
</language>
